spl_manager/__init__.py
spl_manager/__main__.py
spl_manager/_diff_converter.py
spl_manager/apps_manager.py
spl_manager/connection_adapter.py
spl_manager/docker_manager.py
spl_manager/objects.py
spl_manager/samples_manager.py
spl_manager/schemata.py
spl_manager/sync_manager.py
spl_manager-0.1.3.dist-info/entry_points.txt
spl_manager-0.1.3.dist-info/LICENSE
spl_manager-0.1.3.dist-info/WHEEL
spl_manager-0.1.3.dist-info/METADATA
spl_manager-0.1.3.dist-info/RECORD
