Metadata-Version: 2.1
Name: spl-manager
Version: 0.1.3
Summary: A helper for Splunk-related development, maintenance, or migration operations.
Author: Nextpart Security Intelligence
Author-email: info@nextpart.io
Requires-Python: >=3.8,<4.0
Classifier: Programming Language :: Python :: 3
Classifier: Programming Language :: Python :: 3.8
Classifier: Programming Language :: Python :: 3.9
Classifier: Programming Language :: Python :: 3.10
Classifier: Programming Language :: Python :: 3.11
Requires-Dist: Cerberus (>=1.3.0,<1.4.0)
Requires-Dist: deepdiff (>=6.2.0,<6.3.0)
Requires-Dist: docker (>=6.0.0,<6.1.0)
Requires-Dist: dynaconf (>=3.1.0,<3.2.0)
Requires-Dist: fire (>=0.4.0,<0.5.0)
Requires-Dist: inquirerpy (>=0.3.0,<0.4.0)
Requires-Dist: requests-toolbelt (>=0.10.0,<0.11.0)
Requires-Dist: rich (>=12.6.0,<12.7.0)
Requires-Dist: splunk-appinspect (>=2.27.0,<2.28.0)
Requires-Dist: splunk-sdk (>=1.7.0,<1.8.0)
